ekta_chalk/__init__.py
ekta_chalk/py.typed
ekta_chalk-0.1.0.dist-info/METADATA
ekta_chalk-0.1.0.dist-info/WHEEL
ekta_chalk-0.1.0.dist-info/licenses/LICENSE
ekta_chalk-0.1.0.dist-info/RECORD
