Metadata-Version: 2.4
Name: ekta_chalk
Version: 0.1.0
Summary: A simple command-line argument parser inspired by Commander.js
Project-URL: Homepage, https://github.com/AdityaPatange1/ekta_chalk
Project-URL: Documentation, https://github.com/AdityaPatange1/ekta_chalk#readme
Project-URL: Repository, https://github.com/AdityaPatange1/ekta_chalk
Project-URL: Issues, https://github.com/AdityaPatange1/ekta_chalk/issues
Author-email: Your Name <your.email@example.com>
License-Expression: MIT
License-File: LICENSE
Keywords: argparse,argument-parser,cli,command-line,commander
Classifier: Development Status :: 4 - Beta
Classifier: Environment :: Console
Classifier: Intended Audience :: Developers
Classifier: License :: OSI Approved :: MIT License
Classifier: Operating System :: OS Independent
Classifier: Programming Language :: Python :: 3
Classifier: Programming Language :: Python :: 3.10
Classifier: Programming Language :: Python :: 3.11
Classifier: Programming Language :: Python :: 3.12
Classifier: Programming Language :: Python :: 3.13
Classifier: Topic :: Software Development :: Libraries :: Python Modules
Classifier: Topic :: Utilities
Classifier: Typing :: Typed
Requires-Python: >=3.10
Provides-Extra: dev
Requires-Dist: build>=1.0; extra == 'dev'
Requires-Dist: mypy>=1.0; extra == 'dev'
Requires-Dist: pytest>=7.0; extra == 'dev'
Requires-Dist: ruff>=0.1.0; extra == 'dev'
Requires-Dist: twine>=4.0; extra == 'dev'
